pyOutlook/__init__.py
pyOutlook/core/__init__.py
pyOutlook/core/attachment.py
pyOutlook/core/contact.py
pyOutlook/core/folder.py
pyOutlook/core/main.py
pyOutlook/core/message.py
pyOutlook/internal/__init__.py
pyOutlook/internal/errors.py
pyOutlook/internal/utils.py
pyOutlook/services/contact.py
pyOutlook/services/folder.py
pyOutlook/services/message.py
pyoutlook-5.0.0.dist-info/licenses/LICENSE
pyoutlook-5.0.0.dist-info/METADATA
pyoutlook-5.0.0.dist-info/WHEEL
pyoutlook-5.0.0.dist-info/top_level.txt
pyoutlook-5.0.0.dist-info/RECORD
