Metadata-Version: 2.4
Name: pyOutlook
Version: 5.0.0
Summary: A Python module for connecting to the Outlook REST API, without the hassle of dealing with the JSON formatting for requests/responses and the REST endpoints and their varying requirements
Author-email: Jens Astrup <jensaiden@gmail.com>
License: MIT
Project-URL: Homepage, https://pypi.python.org/pypi/pyOutlook
Project-URL: Documentation, http://pyoutlook.readthedocs.io/en/latest/
Keywords: outlook,office365,microsoft,email
Classifier: Development Status :: 5 - Production/Stable
Classifier: Intended Audience :: Developers
Classifier: Topic :: Communications :: Email :: Email Clients (MUA)
Classifier: Topic :: Office/Business
Classifier: License :: OSI Approved :: MIT License
Classifier: Programming Language :: Python :: 3
Classifier: Programming Language :: Python :: 3.10
Classifier: Programming Language :: Python :: 3.11
Classifier: Programming Language :: Python :: 3.12
Classifier: Natural Language :: English
Requires-Python: >=3.10
License-File: LICENSE
Requires-Dist: requests
Requires-Dist: python-dateutil
Provides-Extra: dev
Requires-Dist: coverage; extra == "dev"
Requires-Dist: pytest; extra == "dev"
Requires-Dist: pytest-cov; extra == "dev"
Dynamic: license-file
